{
    "A1": {
        "ID": "A1",
        "desc": "",
        "x": 909.0027849226072,
        "y": 238.90323708611066
    },
    "A2": {
        "ID": "A2",
        "desc": "",
        "x": 3.985356393237555,
        "y": 497.113545211029
    },
    "DC_IN2": {
        "ID": "DC_IN2",
        "desc": "automatic=false",
        "x": 903.0602917230387,
        "y": 508.07811571311913
    },
    "GRAPH:1": {
        "ID": "GRAPH:1",
        "desc": "title=A1 and A2 oscilloscope\nmode=scope\nchannels=2\n# NS*TG= {1, 2, 5, 10, 20, 50, 100, 200, 500, 2000,400} #mS\ntimebase = 3\nNS=1000\nTG=5\nx=time\ny1=A1\ny2=A2\nymin=-8\nymax=8\nfitmode=sine\n\n  ",
        "x": 1133.3266269840599,
        "y": 976.619803926732
    }
}